django_navhelper-1.0.0-py3.11-nspkg.pth
geelweb/django/navhelper/__init__.py
geelweb/django/navhelper/templatetags/__init__.py
geelweb/django/navhelper/templatetags/navactive.py
django_navhelper-1.0.0.dist-info/LICENSE.txt
django_navhelper-1.0.0.dist-info/METADATA
django_navhelper-1.0.0.dist-info/WHEEL
django_navhelper-1.0.0.dist-info/namespace_packages.txt
django_navhelper-1.0.0.dist-info/top_level.txt
django_navhelper-1.0.0.dist-info/RECORD
