Metadata-Version: 2.1
Name: django-navhelper
Version: 1.0.0
Summary: Django template tags designed to help the navigation rendering
Home-page: https://github.com/geelweb/django-navhelper
Download-URL: https://github.com/geelweb/django-navhelper/tarball/1.0.0
Author: Guillaume Luchet
Author-email: <guillaume@geelweb.org>
Maintainer: Guillaume Luchet
Maintainer-email: <guillaume@geelweb.org>
License: MIT
Keywords: django,menu,navigation
License-File: LICENSE.txt
